docker_helper.py
ecs_helper.py
slack_api.py
bravo1996-1.5.data/scripts/golla
commons/__init__.py
commons/config.py
commons/constant.py
utils/__init__.py
utils/helper.py
utils/http_client.py
utils/logger.py
bravo1996-1.5.dist-info/LICENSE
bravo1996-1.5.dist-info/METADATA
bravo1996-1.5.dist-info/WHEEL
bravo1996-1.5.dist-info/top_level.txt
bravo1996-1.5.dist-info/RECORD
