Metadata-Version: 2.1
Name: bravo1996
Version: 1.5
Summary: A Docker and AWS utility package
Home-page: https://github.com/javatechy/dokr
Author: luis bravo
Author-email: bravocolladoluis@gmail.com
License: UNKNOWN
Platform: UNKNOWN
Classifier: Programming Language :: Python :: 3
Classifier: License :: OSI Approved :: MIT License
Classifier: Operating System :: OS Independent
License-File: LICENSE
Requires-Dist: requests
Requires-Dist: click
Requires-Dist: configparser
